ipfs_accelerate_py/__init__.py
ipfs_accelerate_py/ipfs_accelerate.py
libp2p_accelerate_py-0.0.3.dist-info/LICENSE
libp2p_accelerate_py-0.0.3.dist-info/METADATA
libp2p_accelerate_py-0.0.3.dist-info/WHEEL
libp2p_accelerate_py-0.0.3.dist-info/top_level.txt
libp2p_accelerate_py-0.0.3.dist-info/RECORD
